copulalib/__init__.py
copulalib/copulalib.py
copulalib-2.0.1.dist-info/LICENSE
copulalib-2.0.1.dist-info/METADATA
copulalib-2.0.1.dist-info/WHEEL
copulalib-2.0.1.dist-info/top_level.txt
copulalib-2.0.1.dist-info/RECORD
