Metadata-Version: 2.1
Name: copulalib
Version: 2.0.1
Summary: A library for the copula
Author-email: Sat Kumar Tomer <satkumartomer@gmail.com>
Project-URL: Homepage, https://github.com/tomersk/copulalib
Project-URL: Bug Tracker, https://github.com/tomersk/copulalib/issues
Classifier: Programming Language :: Python :: 3
Classifier: License :: OSI Approved :: GNU Library or Lesser General Public License (LGPL)
Classifier: Operating System :: OS Independent
Classifier: Topic :: Scientific/Engineering
Classifier: Development Status :: 4 - Beta
Classifier: Intended Audience :: Science/Research
Requires-Python: >=3.7
License-File: LICENSE
